epytext2rst.py
setup.py
epytext2rst.egg-info/PKG-INFO
epytext2rst.egg-info/SOURCES.txt
epytext2rst.egg-info/dependency_links.txt
epytext2rst.egg-info/top_level.txt