Metadata-Version: 1.0
Name: epytext2rst
Version: 1.0.2
Summary: Convert epytext markup language in RestructuredText
Home-page: https://bitbucket.org/mrleeh/epytext2rst
Author: Stefan Lehmann
Author-email: Stefan.St.Lehmann@gmail.com
License: GPL
Platform: UNKNOWN
